transformerlab_client/__init__.py
transformerlab_client/client.py
transformerlab_client/callbacks/__init__.py
transformerlab_client/callbacks/hf_callback.py
transformerlab_client/rpc_clients/__init__.py
transformerlab_client/rpc_clients/retry_client.py
transformerlab_client-0.1.4.dist-info/licenses/LICENSE
transformerlab_client-0.1.4.dist-info/METADATA
transformerlab_client-0.1.4.dist-info/WHEEL
transformerlab_client-0.1.4.dist-info/top_level.txt
transformerlab_client-0.1.4.dist-info/RECORD
