Metadata-Version: 2.4
Name: transformerlab-client
Version: 0.1.4
Summary: Python SDK client for running remote jobs on Transformer Lab.
Author-email: "Transformer Lab Inc." <developers@transformerlab.ai>
License:                     GNU AFFERO GENERAL PUBLIC LICENSE
Project-URL: Homepage, https://github.com/transformerlab/transformerlab-client
Project-URL: Bug Tracker, https://github.com/transformerlab/transformerlab-client/issues
Requires-Python: >=3.10
License-File: LICENSE
Requires-Dist: transformers
Dynamic: license-file
